DDFR/__init__.py
DDFR/ddfr.py
DDFR/gridweights.py
ddfrvn-1.1.0.dist-info/licenses/LICENSE
ddfrvn-1.1.0.dist-info/METADATA
ddfrvn-1.1.0.dist-info/WHEEL
ddfrvn-1.1.0.dist-info/entry_points.txt
ddfrvn-1.1.0.dist-info/top_level.txt
ddfrvn-1.1.0.dist-info/RECORD
