Metadata-Version: 2.4
Name: ddfrvn
Version: 1.1.0
Summary: A CLI tool for downloading and processing Daymet NetCDF files for the Raven hydrological modelling framework.
Home-page: https://github.com/Scriptbash/DaymetDownloaderForRaven
Author: Francis Lapointe
Author-email: francis.lapointe5@usherbrooke.ca
Project-URL: Bug Reports, https://github.com/Scriptbash/DaymetDownloaderForRaven/issues
Project-URL: Funding, https://ko-fi.com/scriptbash
Project-URL: Source, https://github.com/Scriptbash/DaymetDownloaderForRaven
Keywords: daymet,raven,hydrology
Classifier: Programming Language :: Python :: 3
Classifier: License :: OSI Approved :: MIT License
Classifier: Operating System :: OS Independent
Requires-Python: >=3.6
License-File: LICENSE
Requires-Dist: numpy
Requires-Dist: dask
Requires-Dist: xarray
Requires-Dist: pandas
Requires-Dist: geopandas
Requires-Dist: shapely
Requires-Dist: netCDF4
Requires-Dist: scipy
Dynamic: author
Dynamic: author-email
Dynamic: classifier
Dynamic: description
Dynamic: description-content-type
Dynamic: home-page
Dynamic: keywords
Dynamic: license-file
Dynamic: project-url
Dynamic: requires-dist
Dynamic: requires-python
Dynamic: summary
